{
    "user_id": "user90302",
    "average_retweet_count": "94",
    "average_favorite_count": "490",
    "followers_count": "777",
    "verified": "False",
    "influence_score": "1361",
    "follower_list": [
        "user32991",
        "user51358",
        "user75654",
        "user939",
        "user7209",
        "user43934",
        "user27428",
        "user50257",
        "user24792",
        "user86776",
        "user56578",
        "user36617",
        "user67227",
        "user98042",
        "user90589",
        "user71837",
        "user72004",
        "user7003",
        "user98013",
        "user23510",
        "user50371",
        "user86594",
        "user2357",
        "user54068",
        "user77271",
        "user54693",
        "user45037",
        "user66966",
        "user69597",
        "user51052",
        "user10717",
        "user19843",
        "user53062",
        "user95084",
        "user35358",
        "user84921",
        "user53035",
        "user43931",
        "user32825",
        "user84788",
        "user42807",
        "user48128",
        "user11756",
        "user7597",
        "user722",
        "user30676",
        "user73771",
        "user44743",
        "user79014",
        "user2354",
        "user65897",
        "user7444",
        "user78814",
        "user84827",
        "user41278",
        "user32363",
        "user45007",
        "user69490",
        "user70613",
        "user93122",
        "user24319",
        "user90039",
        "user48350",
        "user39848",
        "user7698",
        "user27034",
        "user65627",
        "user30176",
        "user43824",
        "user73339",
        "user73595",
        "user6349",
        "user22255",
        "user74131",
        "user87985",
        "user37609",
        "user81765",
        "user43570",
        "user71738",
        "user44657",
        "user21323",
        "user33360",
        "user26190",
        "user13152",
        "user80938",
        "user93832",
        "user75599",
        "user54218",
        "user94699",
        "user97737",
        "user95138",
        "user65578",
        "user74176",
        "user6560",
        "user87104",
        "user83271",
        "user75372",
        "user88112",
        "user58505",
        "user94394",
        "user95742",
        "user93593",
        "user6747",
        "user96384",
        "user34820",
        "user59004",
        "user58690",
        "user57395",
        "user55714",
        "user88930",
        "user20152",
        "user13666",
        "user61305",
        "user41860",
        "user47715",
        "user681",
        "user44091",
        "user8054",
        "user66607",
        "user11340",
        "user61596",
        "user45369",
        "user59166",
        "user89511",
        "user79997",
        "user76034",
        "user3558",
        "user78487",
        "user79012",
        "user74365",
        "user35715",
        "user22688",
        "user79330",
        "user14239",
        "user66050",
        "user4272",
        "user78915",
        "user98510",
        "user84468",
        "user89986",
        "user45307",
        "user42932",
        "user32067",
        "user62767",
        "user1014",
        "user69945",
        "user55692",
        "user94195",
        "user69599",
        "user61469",
        "user84873",
        "user31025",
        "user68569",
        "user89283",
        "user83274",
        "user77594",
        "user61789",
        "user49965",
        "user92029",
        "user57937",
        "user77922",
        "user10382",
        "user6184",
        "user12271",
        "user14053",
        "user35094",
        "user70381",
        "user84391",
        "user71633",
        "user31549",
        "user69984",
        "user78095",
        "user859",
        "user28333",
        "user91416",
        "user57874",
        "user49983",
        "user30620",
        "user5804",
        "user43589",
        "user7685",
        "user35995",
        "user12581",
        "user74535",
        "user29897",
        "user67179",
        "user31965",
        "user67360",
        "user54898",
        "user9154",
        "user87167",
        "user29467",
        "user52457",
        "user67249",
        "user38672",
        "user44932",
        "user80323",
        "user4416",
        "user59385",
        "user69555",
        "user27088",
        "user46472",
        "user99239",
        "user22791",
        "user57764",
        "user35395",
        "user41938",
        "user87669",
        "user7099",
        "user88064",
        "user13462",
        "user62327",
        "user36537",
        "user31689",
        "user29197",
        "user32256",
        "user55662",
        "user22017",
        "user43533",
        "user39531",
        "user79419",
        "user17801",
        "user21716",
        "user30868",
        "user21091",
        "user87704",
        "user2348",
        "user28148",
        "user50935",
        "user65346",
        "user77148",
        "user74700",
        "user6378",
        "user66414",
        "user58364",
        "user65751",
        "user68512",
        "user98972",
        "user97368",
        "user43720",
        "user99141",
        "user80949",
        "user51924",
        "user25591",
        "user7906",
        "user65907",
        "user31410",
        "user87805",
        "user37740",
        "user3347",
        "user1026",
        "user82013",
        "user12525",
        "user33594",
        "user43376",
        "user30533",
        "user54971",
        "user18053",
        "user48497",
        "user56026",
        "user34390",
        "user55552",
        "user9035",
        "user74770",
        "user27430",
        "user16810",
        "user66099",
        "user70633",
        "user41266",
        "user89776",
        "user58322",
        "user87054",
        "user87120",
        "user99317",
        "user33625",
        "user43441",
        "user95926",
        "user33264",
        "user37277",
        "user11593",
        "user52598",
        "user89770",
        "user60782",
        "user65550",
        "user28959",
        "user64534",
        "user96006",
        "user31679",
        "user88225",
        "user49434",
        "user8033",
        "user28140",
        "user56942",
        "user48784",
        "user96501",
        "user10508",
        "user13852",
        "user46828",
        "user68258",
        "user28205",
        "user94825",
        "user18462",
        "user61266",
        "user93228",
        "user18556",
        "user15648",
        "user46189",
        "user67005",
        "user42660",
        "user94295",
        "user51812",
        "user67896",
        "user26058",
        "user5191",
        "user7028",
        "user27101",
        "user29817",
        "user6584",
        "user35885",
        "user8819",
        "user8596",
        "user94514",
        "user92296",
        "user29095",
        "user20734",
        "user77835",
        "user28720",
        "user54255",
        "user49789",
        "user73762",
        "user36472",
        "user25036",
        "user59686",
        "user18106",
        "user94857",
        "user75649",
        "user20524",
        "user66992",
        "user11807",
        "user62992",
        "user18569",
        "user96487",
        "user31007",
        "user52136",
        "user40080",
        "user51859",
        "user72832",
        "user49322",
        "user66742",
        "user36871",
        "user10275",
        "user97130",
        "user99154",
        "user62448",
        "user41761",
        "user83595",
        "user10774",
        "user48253",
        "user98833",
        "user59655",
        "user95183",
        "user89332",
        "user96521",
        "user21412",
        "user760",
        "user76132",
        "user49890",
        "user42574",
        "user8244",
        "user9595",
        "user67463",
        "user59713",
        "user99971",
        "user33890",
        "user65031",
        "user61110",
        "user54873",
        "user713",
        "user90236",
        "user16351",
        "user50278",
        "user10565",
        "user73920",
        "user9044",
        "user25187",
        "user58666",
        "user41083",
        "user44760",
        "user63110",
        "user96233",
        "user90135",
        "user90520",
        "user36170",
        "user74463",
        "user7413",
        "user86352",
        "user40895",
        "user58962",
        "user74453",
        "user27070",
        "user42275",
        "user28898",
        "user63038",
        "user78684",
        "user77790",
        "user61590",
        "user59417",
        "user93970",
        "user59534",
        "user14869",
        "user88557",
        "user30614",
        "user61146",
        "user66465",
        "user49554",
        "user38203",
        "user38321",
        "user37583",
        "user41076",
        "user97113",
        "user34438",
        "user22307",
        "user90070",
        "user7389",
        "user33935",
        "user91956",
        "user61505",
        "user77538",
        "user68284",
        "user73611",
        "user81762",
        "user87295",
        "user52854",
        "user47936",
        "user8910",
        "user19891",
        "user86008",
        "user56326",
        "user95019",
        "user9803",
        "user56737",
        "user98564",
        "user79554",
        "user71999",
        "user17361",
        "user10323",
        "user85715",
        "user90750",
        "user66762",
        "user80751",
        "user91011",
        "user30248",
        "user77894",
        "user67363",
        "user3537",
        "user49487",
        "user79083",
        "user30219",
        "user10316",
        "user40889",
        "user21211",
        "user50495",
        "user33108",
        "user71478",
        "user50809",
        "user79043",
        "user57994",
        "user84075",
        "user36165",
        "user92549",
        "user25280",
        "user85711",
        "user10765",
        "user62594",
        "user52613",
        "user73995",
        "user53674",
        "user80983",
        "user49478",
        "user28238",
        "user97629",
        "user91137",
        "user44999",
        "user75872",
        "user83741",
        "user60532",
        "user81253",
        "user25323",
        "user18060",
        "user8717",
        "user71214",
        "user15445",
        "user47161",
        "user87981",
        "user46298",
        "user45798",
        "user12496",
        "user63067",
        "user34688",
        "user36019",
        "user3004",
        "user41531",
        "user64206",
        "user23469",
        "user22033",
        "user26930",
        "user21696",
        "user14993",
        "user59550",
        "user40905",
        "user3237",
        "user37026",
        "user48040",
        "user82762",
        "user87173",
        "user99414",
        "user66975",
        "user28563",
        "user11743",
        "user87570",
        "user66210",
        "user93320",
        "user35621",
        "user65842",
        "user7077",
        "user67503",
        "user55941",
        "user96416",
        "user7777",
        "user87721",
        "user63846",
        "user4152",
        "user49043",
        "user64446",
        "user62986",
        "user21242",
        "user5029",
        "user65661",
        "user18052",
        "user77479",
        "user59867",
        "user1581",
        "user81511",
        "user31361",
        "user26734",
        "user2231",
        "user42063",
        "user93401",
        "user8678",
        "user91236",
        "user44595",
        "user4062",
        "user79375",
        "user14597",
        "user65331",
        "user75055",
        "user35391",
        "user12227",
        "user3285",
        "user32754",
        "user94276",
        "user53790",
        "user11580",
        "user88326",
        "user20723",
        "user71745",
        "user95617",
        "user98156",
        "user99812",
        "user29244",
        "user85686",
        "user97604",
        "user88586",
        "user40213",
        "user57127",
        "user99704",
        "user43163",
        "user69422",
        "user19647",
        "user74743",
        "user6006",
        "user52635",
        "user98974",
        "user46150",
        "user91639",
        "user89045",
        "user78914",
        "user85608",
        "user80465",
        "user66759",
        "user50121",
        "user15530",
        "user96503",
        "user56307",
        "user83758",
        "user40093",
        "user25979",
        "user46773",
        "user57086",
        "user53915",
        "user81235",
        "user89190",
        "user30001",
        "user34799",
        "user94786",
        "user93185",
        "user15122",
        "user58815",
        "user32165",
        "user24398",
        "user80896",
        "user2781",
        "user69435",
        "user46553",
        "user27274",
        "user75678",
        "user4212",
        "user96871",
        "user90690",
        "user58785",
        "user99720",
        "user33127",
        "user42670",
        "user76587",
        "user76243",
        "user80703",
        "user8506",
        "user51476",
        "user1938",
        "user97526",
        "user68894",
        "user15647",
        "user66430",
        "user53148",
        "user61021",
        "user33942",
        "user38009",
        "user65426",
        "user19787",
        "user30263",
        "user27936",
        "user34079",
        "user59295",
        "user7285",
        "user95448",
        "user15664",
        "user49980",
        "user71541",
        "user85975",
        "user16685",
        "user81418",
        "user75181",
        "user24338",
        "user62154",
        "user74281",
        "user94324",
        "user1302",
        "user19997",
        "user41518",
        "user92125",
        "user5046",
        "user66851",
        "user3087",
        "user50406",
        "user93186",
        "user78967",
        "user41342",
        "user76626",
        "user56541",
        "user96714",
        "user80672",
        "user16273",
        "user71376",
        "user754",
        "user31565",
        "user86949",
        "user61748",
        "user69321",
        "user64086",
        "user34730",
        "user67976",
        "user70263",
        "user17153",
        "user87057",
        "user58723",
        "user45179",
        "user59985",
        "user98738",
        "user56197",
        "user7021",
        "user91155",
        "user44945",
        "user32046",
        "user6133",
        "user55989",
        "user64253",
        "user85047",
        "user28399",
        "user24439",
        "user45254",
        "user98884",
        "user29991",
        "user43817",
        "user34851",
        "user31376",
        "user12904",
        "user6914",
        "user55588",
        "user99352",
        "user78791",
        "user3309",
        "user82676",
        "user37411",
        "user61809",
        "user77242",
        "user40693",
        "user91659",
        "user89598",
        "user22447",
        "user9816",
        "user94639",
        "user10942",
        "user60481",
        "user74435",
        "user11147",
        "user73263",
        "user96472",
        "user10226",
        "user93086",
        "user6303",
        "user43059",
        "user91932",
        "user78912",
        "user85893",
        "user47194",
        "user79848",
        "user70779",
        "user39517",
        "user99561",
        "user80117",
        "user939",
        "user50857",
        "user91190",
        "user58509",
        "user72452",
        "user68741",
        "user74210",
        "user86610",
        "user92790",
        "user31253",
        "user34115",
        "user73773",
        "user94232",
        "user38025",
        "user55412",
        "user83670",
        "user77451",
        "user58172",
        "user53773",
        "user63558",
        "user84007",
        "user71309",
        "user22592",
        "user3715",
        "user99195",
        "user35909",
        "user86020",
        "user52299",
        "user9177",
        "user23670",
        "user43811",
        "user16978",
        "user14753",
        "user92490",
        "user67809",
        "user90733",
        "user19284"
    ]
}