{
    "user_id": "user78053",
    "average_retweet_count": "24",
    "average_favorite_count": "195",
    "followers_count": "779",
    "verified": "True",
    "influence_score": "998",
    "follower_list": [
        "user68147",
        "user1283",
        "user97658",
        "user41974",
        "user47463",
        "user57498",
        "user97094",
        "user36910",
        "user67859",
        "user81765",
        "user14623",
        "user740",
        "user35008",
        "user28389",
        "user16362",
        "user89193",
        "user33190",
        "user28785",
        "user66975",
        "user11645",
        "user35342",
        "user45317",
        "user78473",
        "user83644",
        "user19996",
        "user25505",
        "user60752",
        "user33542",
        "user82775",
        "user19683",
        "user73654",
        "user48914",
        "user74802",
        "user76989",
        "user67717",
        "user64155",
        "user58908",
        "user12656",
        "user21716",
        "user86208",
        "user19836",
        "user46812",
        "user21117",
        "user82642",
        "user78779",
        "user16837",
        "user82501",
        "user76655",
        "user26680",
        "user32518",
        "user59760",
        "user45376",
        "user82062",
        "user65661",
        "user89855",
        "user11059",
        "user83156",
        "user88085",
        "user95611",
        "user81214",
        "user33634",
        "user33877",
        "user4497",
        "user22910",
        "user48611",
        "user81883",
        "user1327",
        "user68865",
        "user65305",
        "user80727",
        "user56430",
        "user49151",
        "user9630",
        "user98169",
        "user48755",
        "user62848",
        "user42727",
        "user82917",
        "user34702",
        "user27509",
        "user90485",
        "user93555",
        "user8982",
        "user64331",
        "user29241",
        "user36347",
        "user16031",
        "user35526",
        "user40268",
        "user17802",
        "user95254",
        "user28339",
        "user68723",
        "user56535",
        "user96814",
        "user40823",
        "user57269",
        "user22492",
        "user59878",
        "user19063",
        "user84021",
        "user80989",
        "user9414",
        "user35312",
        "user72783",
        "user78444",
        "user79660",
        "user20933",
        "user70719",
        "user7118",
        "user41931",
        "user99142",
        "user20473",
        "user24338",
        "user81553",
        "user84817",
        "user75735",
        "user41487",
        "user25645",
        "user26034",
        "user44193",
        "user5152",
        "user82453",
        "user1409",
        "user77341",
        "user95235",
        "user54235",
        "user35169",
        "user43743",
        "user6461",
        "user64531",
        "user57966",
        "user76368",
        "user75470",
        "user65051",
        "user2172",
        "user50780",
        "user42738",
        "user51632",
        "user31381",
        "user81443",
        "user22868",
        "user75600",
        "user37593",
        "user74546",
        "user2346",
        "user83231",
        "user43216",
        "user11909",
        "user58383",
        "user12362",
        "user72282",
        "user27102",
        "user2095",
        "user63390",
        "user9534",
        "user27787",
        "user88344",
        "user83085",
        "user96179",
        "user50444",
        "user59394",
        "user89944",
        "user11821",
        "user42232",
        "user62241",
        "user69199",
        "user11490",
        "user28316",
        "user11193",
        "user53569",
        "user48878",
        "user96020",
        "user99923",
        "user74153",
        "user7677",
        "user17319",
        "user40936",
        "user65903",
        "user64199",
        "user6074",
        "user52734",
        "user22324",
        "user60427",
        "user40164",
        "user41576",
        "user46169",
        "user83480",
        "user66172",
        "user71881",
        "user78232",
        "user36970",
        "user26220",
        "user24122",
        "user24420",
        "user80097",
        "user59508",
        "user55499",
        "user70720",
        "user29633",
        "user72525",
        "user43338",
        "user18242",
        "user93348",
        "user51502",
        "user48771",
        "user25265",
        "user6599",
        "user35870",
        "user92383",
        "user73744",
        "user10647",
        "user26279",
        "user10435",
        "user41489",
        "user4866",
        "user80485",
        "user8049",
        "user12533",
        "user76601",
        "user38714",
        "user35526",
        "user81384",
        "user56132",
        "user53735",
        "user12334",
        "user62620",
        "user47591",
        "user84322",
        "user19702",
        "user91686",
        "user51297",
        "user37059",
        "user56421",
        "user54863",
        "user60189",
        "user35589",
        "user75934",
        "user29579",
        "user28360",
        "user52009",
        "user5161",
        "user11955",
        "user50024",
        "user99223",
        "user7431",
        "user23268",
        "user70736",
        "user88671",
        "user79945",
        "user98148",
        "user57007",
        "user39460",
        "user38712",
        "user68710",
        "user31606",
        "user9702",
        "user40047",
        "user30530",
        "user47598",
        "user10988",
        "user23251",
        "user86351",
        "user90219",
        "user53401",
        "user37140",
        "user78889",
        "user9328",
        "user33508",
        "user28136",
        "user26644",
        "user74999",
        "user78712",
        "user87493",
        "user18703",
        "user46080",
        "user43580",
        "user63716",
        "user11548",
        "user34836",
        "user66194",
        "user94707",
        "user99855",
        "user49824",
        "user89064",
        "user25410",
        "user20296",
        "user30665",
        "user29759",
        "user45147",
        "user92707",
        "user11760",
        "user472",
        "user45404",
        "user79703",
        "user2223",
        "user51492",
        "user29344",
        "user85140",
        "user99011",
        "user1883",
        "user93851",
        "user14580",
        "user8299",
        "user61376",
        "user82183",
        "user5346",
        "user46733",
        "user32463",
        "user73010",
        "user54960",
        "user79570",
        "user4165",
        "user68477",
        "user97038",
        "user57224",
        "user18693",
        "user97434",
        "user57133",
        "user76730",
        "user68833",
        "user67544",
        "user51021",
        "user49083",
        "user97397",
        "user16185",
        "user46795",
        "user33865",
        "user26073",
        "user92128",
        "user4784",
        "user75349",
        "user61106",
        "user39351",
        "user5798",
        "user28645",
        "user84702",
        "user69085",
        "user12971",
        "user66162",
        "user20616",
        "user62052",
        "user26059",
        "user7246",
        "user3386",
        "user88327",
        "user71596",
        "user878",
        "user60040",
        "user93391",
        "user45435",
        "user22733",
        "user645",
        "user77933",
        "user5371",
        "user69609",
        "user41034",
        "user32197",
        "user65134",
        "user18804",
        "user37486",
        "user35902",
        "user22709",
        "user77209",
        "user30093",
        "user88066",
        "user12282",
        "user55155",
        "user34056",
        "user98997",
        "user34910",
        "user89811",
        "user49775",
        "user11075",
        "user72680",
        "user81460",
        "user47489",
        "user31757",
        "user83497",
        "user98084",
        "user21293",
        "user82989",
        "user12786",
        "user67673",
        "user14413",
        "user82658",
        "user15531",
        "user73737",
        "user50442",
        "user70597",
        "user83217",
        "user4726",
        "user97906",
        "user65701",
        "user51520",
        "user6236",
        "user97191",
        "user30632",
        "user10613",
        "user55577",
        "user18284",
        "user3217",
        "user34309",
        "user84006",
        "user54077",
        "user62266",
        "user14579",
        "user15964",
        "user6219",
        "user2435",
        "user67873",
        "user9220",
        "user5741",
        "user25265",
        "user14630",
        "user15520",
        "user94763",
        "user85697",
        "user40943",
        "user6472",
        "user48082",
        "user75974",
        "user75919",
        "user90424",
        "user36608",
        "user3439",
        "user9016",
        "user53314",
        "user43019",
        "user56341",
        "user54478",
        "user58588",
        "user83768",
        "user88483",
        "user74278",
        "user63237",
        "user21227",
        "user3944",
        "user81298",
        "user52235",
        "user79935",
        "user40619",
        "user17403",
        "user75629",
        "user56328",
        "user60553",
        "user1364",
        "user12856",
        "user68670",
        "user41846",
        "user90978",
        "user36694",
        "user47356",
        "user24585",
        "user61371",
        "user34031",
        "user99378",
        "user95144",
        "user78579",
        "user53313",
        "user77168",
        "user533",
        "user70785",
        "user8139",
        "user61794",
        "user98789",
        "user91704",
        "user73761",
        "user78026",
        "user3424",
        "user35429",
        "user71338",
        "user5865",
        "user48817",
        "user18135",
        "user21240",
        "user26213",
        "user24129",
        "user59383",
        "user28959",
        "user72269",
        "user85873",
        "user21026",
        "user46260",
        "user63337",
        "user86865",
        "user44714",
        "user49978",
        "user36280",
        "user36761",
        "user48670",
        "user57334",
        "user82053",
        "user86861",
        "user62865",
        "user46382",
        "user18328",
        "user35717",
        "user49220",
        "user50814",
        "user36577",
        "user10112",
        "user25223",
        "user47121",
        "user79871",
        "user43010",
        "user12150",
        "user88354",
        "user51457",
        "user19217",
        "user46117",
        "user98810",
        "user92814",
        "user92261",
        "user20950",
        "user88617",
        "user49926",
        "user53515",
        "user34456",
        "user18088",
        "user10729",
        "user64092",
        "user27360",
        "user10152",
        "user11495",
        "user99674",
        "user73754",
        "user69726",
        "user80320",
        "user89609",
        "user33675",
        "user19360",
        "user66898",
        "user67396",
        "user10896",
        "user76023",
        "user92669",
        "user99348",
        "user10382",
        "user18661",
        "user68242",
        "user46374",
        "user38352",
        "user42918",
        "user2948",
        "user57959",
        "user99126",
        "user75586",
        "user84503",
        "user42145",
        "user48929",
        "user15477",
        "user58481",
        "user61624",
        "user61756",
        "user54316",
        "user93435",
        "user62321",
        "user53246",
        "user46596",
        "user59061",
        "user87697",
        "user98112",
        "user43155",
        "user4266",
        "user92874",
        "user86069",
        "user63164",
        "user72890",
        "user55478",
        "user64289",
        "user96384",
        "user68056",
        "user64097",
        "user27834",
        "user61398",
        "user15430",
        "user19205",
        "user14271",
        "user42252",
        "user34421",
        "user83361",
        "user84705",
        "user69619",
        "user69358",
        "user92744",
        "user2423",
        "user74682",
        "user9740",
        "user76087",
        "user14538",
        "user93543",
        "user37304",
        "user7938",
        "user45610",
        "user96931",
        "user10133",
        "user14526",
        "user63363",
        "user84005",
        "user70034",
        "user51963",
        "user25401",
        "user21793",
        "user90001",
        "user46309",
        "user62111",
        "user62550",
        "user89799",
        "user72121",
        "user83055",
        "user4203",
        "user76809",
        "user15376",
        "user30854",
        "user45933",
        "user25185",
        "user42539",
        "user22912",
        "user66374",
        "user87285",
        "user87620",
        "user70848",
        "user52102",
        "user25761",
        "user57627",
        "user6541",
        "user72222",
        "user97118",
        "user24037",
        "user60315",
        "user28501",
        "user58994",
        "user59607",
        "user72697",
        "user92106",
        "user75879",
        "user73636",
        "user10217",
        "user70036",
        "user44848",
        "user28682",
        "user70259",
        "user85237",
        "user78395",
        "user53236",
        "user8625",
        "user65433",
        "user2770",
        "user44693",
        "user53876",
        "user30571",
        "user94436",
        "user86547",
        "user90623",
        "user94332",
        "user62149",
        "user16620",
        "user21582",
        "user85883",
        "user73449",
        "user4358",
        "user14211",
        "user94086",
        "user93799",
        "user64337",
        "user59417",
        "user9206",
        "user51310",
        "user68413",
        "user71713",
        "user4758",
        "user88450",
        "user83250",
        "user31486",
        "user98044",
        "user7297",
        "user78083",
        "user40093",
        "user92654",
        "user43343",
        "user28053",
        "user4814",
        "user56686",
        "user31906",
        "user2368",
        "user19824",
        "user29517",
        "user21675",
        "user10370",
        "user71004",
        "user43184",
        "user88161",
        "user46047",
        "user95402",
        "user51975",
        "user11952",
        "user90922",
        "user23356",
        "user26801",
        "user89398",
        "user51537",
        "user60404",
        "user55284",
        "user6856",
        "user54520",
        "user48521",
        "user43557",
        "user41896",
        "user77254",
        "user28299",
        "user48778",
        "user30208",
        "user94885",
        "user77506",
        "user67336",
        "user57455",
        "user94238",
        "user19784",
        "user1872",
        "user97067",
        "user78432",
        "user15855",
        "user79864",
        "user61408",
        "user23658",
        "user38496",
        "user59415",
        "user25982",
        "user53981",
        "user67838",
        "user31097",
        "user96510",
        "user62018",
        "user17129",
        "user15387",
        "user51193",
        "user70618",
        "user74323",
        "user60626",
        "user44652",
        "user84379",
        "user20415",
        "user81065",
        "user95788",
        "user92541",
        "user27811",
        "user28432",
        "user91789",
        "user14592",
        "user12413",
        "user86905",
        "user74885",
        "user2825",
        "user66166",
        "user38557",
        "user25291",
        "user46303",
        "user76776",
        "user43380",
        "user69275",
        "user92310",
        "user11869",
        "user75916",
        "user72147",
        "user2727",
        "user46885",
        "user27510",
        "user53975",
        "user48001",
        "user43778",
        "user84518",
        "user66676",
        "user98574",
        "user29439",
        "user81293",
        "user67903",
        "user97136",
        "user21396"
    ]
}