{
    "user_id": "user86530",
    "average_retweet_count": "142",
    "average_favorite_count": "261",
    "followers_count": "313",
    "verified": "False",
    "influence_score": "716",
    "follower_list": [
        "user83444",
        "user71835",
        "user67497",
        "user33657",
        "user50566",
        "user72178",
        "user13897",
        "user2333",
        "user58772",
        "user37892",
        "user81181",
        "user96426",
        "user91726",
        "user75404",
        "user17331",
        "user12412",
        "user1755",
        "user18724",
        "user91786",
        "user37172",
        "user37229",
        "user61797",
        "user74258",
        "user48175",
        "user96259",
        "user42097",
        "user34919",
        "user27158",
        "user87399",
        "user83311",
        "user72205",
        "user48847",
        "user46498",
        "user87585",
        "user42591",
        "user25727",
        "user74387",
        "user377",
        "user65483",
        "user78018",
        "user82570",
        "user70989",
        "user89640",
        "user84899",
        "user57627",
        "user21915",
        "user5395",
        "user97536",
        "user46260",
        "user10677",
        "user91443",
        "user35910",
        "user15391",
        "user78171",
        "user82165",
        "user62671",
        "user95290",
        "user2831",
        "user29115",
        "user72509",
        "user75134",
        "user63237",
        "user27324",
        "user37229",
        "user85591",
        "user2392",
        "user37349",
        "user53448",
        "user76920",
        "user226",
        "user34910",
        "user22876",
        "user8498",
        "user95942",
        "user44007",
        "user36204",
        "user10271",
        "user21357",
        "user67003",
        "user82453",
        "user87066",
        "user37446",
        "user95082",
        "user1091",
        "user82462",
        "user53462",
        "user99502",
        "user57705",
        "user1183",
        "user30643",
        "user94258",
        "user28211",
        "user40066",
        "user5608",
        "user50279",
        "user14205",
        "user27463",
        "user67727",
        "user38005",
        "user53260",
        "user20663",
        "user98764",
        "user23043",
        "user90837",
        "user77687",
        "user35783",
        "user70079",
        "user72352",
        "user5018",
        "user12512",
        "user88226",
        "user59354",
        "user83723",
        "user39269",
        "user36713",
        "user19030",
        "user77022",
        "user74551",
        "user83571",
        "user18338",
        "user58780",
        "user38232",
        "user1306",
        "user69816",
        "user86395",
        "user40092",
        "user38075",
        "user75200",
        "user36596",
        "user67279",
        "user93255",
        "user60901",
        "user18926",
        "user57666",
        "user81737",
        "user37979",
        "user70728",
        "user30180",
        "user54424",
        "user96730",
        "user60237",
        "user67340",
        "user11272",
        "user58526",
        "user5480",
        "user71089",
        "user14870",
        "user52450",
        "user30136",
        "user91907",
        "user55318",
        "user27662",
        "user47705",
        "user93051",
        "user85728",
        "user34519",
        "user59008",
        "user56949",
        "user24146",
        "user11697",
        "user67063",
        "user56002",
        "user10885",
        "user46320",
        "user7602",
        "user54241",
        "user32776",
        "user46720",
        "user12141",
        "user71428",
        "user20085",
        "user19934",
        "user82416",
        "user5263",
        "user88681",
        "user46344",
        "user30342",
        "user32974",
        "user63255",
        "user62315",
        "user78411",
        "user49814",
        "user73341",
        "user2037",
        "user48602",
        "user13023",
        "user80511",
        "user24763",
        "user64412",
        "user99930",
        "user66171",
        "user21425",
        "user29818",
        "user76254",
        "user35097",
        "user49332",
        "user24167",
        "user89584",
        "user47127",
        "user58284",
        "user60635",
        "user42823",
        "user1216",
        "user19360",
        "user35445",
        "user17345",
        "user47988",
        "user11782",
        "user60164",
        "user12728",
        "user69137",
        "user21564",
        "user91877",
        "user20851",
        "user12453",
        "user86332",
        "user13806",
        "user75012",
        "user92541",
        "user2629",
        "user20283",
        "user26245",
        "user12231",
        "user32517",
        "user18594",
        "user79861",
        "user49312",
        "user95123",
        "user27778",
        "user31670",
        "user28511",
        "user51807",
        "user67329",
        "user33998",
        "user4865",
        "user21026",
        "user92419",
        "user81943",
        "user13332",
        "user88304",
        "user41826",
        "user37482",
        "user56777",
        "user10760",
        "user86908",
        "user13854",
        "user84434",
        "user89636",
        "user23419",
        "user83032",
        "user13315",
        "user98492",
        "user70905",
        "user18781",
        "user81377",
        "user89006",
        "user72517",
        "user19740",
        "user78102",
        "user83229",
        "user21054",
        "user18614",
        "user29675",
        "user76382",
        "user67707",
        "user39453",
        "user91537",
        "user8549",
        "user96697",
        "user30695",
        "user69304",
        "user60831",
        "user9811",
        "user57664",
        "user75582",
        "user83384",
        "user40813",
        "user4850",
        "user95584",
        "user67418",
        "user33630",
        "user87086",
        "user96901",
        "user30614",
        "user86039",
        "user74595",
        "user96051",
        "user28466",
        "user70398",
        "user56220",
        "user21188",
        "user58618",
        "user86236",
        "user48868",
        "user70449",
        "user25102",
        "user31492",
        "user39925",
        "user44098",
        "user8279",
        "user99169",
        "user65307",
        "user13806",
        "user77629",
        "user23259",
        "user65470",
        "user85331",
        "user56768",
        "user7474",
        "user40573",
        "user82943",
        "user30671",
        "user17907"
    ]
}