{
    "user_id": "user77235",
    "average_retweet_count": "11",
    "average_favorite_count": "26",
    "followers_count": "156",
    "verified": "False",
    "influence_score": "193",
    "follower_list": [
        "user83729",
        "user74426",
        "user46357",
        "user86887",
        "user7091",
        "user6624",
        "user66177",
        "user14027",
        "user33092",
        "user6553",
        "user53242",
        "user73907",
        "user60962",
        "user22325",
        "user10728",
        "user16459",
        "user37024",
        "user55272",
        "user47821",
        "user47542",
        "user37955",
        "user23838",
        "user11481",
        "user60610",
        "user32739",
        "user26058",
        "user53157",
        "user72326",
        "user70707",
        "user77078",
        "user95598",
        "user31845",
        "user46008",
        "user11384",
        "user46206",
        "user99387",
        "user38817",
        "user40285",
        "user70480",
        "user77880",
        "user72412",
        "user60846",
        "user7074",
        "user99653",
        "user18650",
        "user28285",
        "user51760",
        "user34788",
        "user29395",
        "user63352",
        "user36131",
        "user94896",
        "user53582",
        "user19198",
        "user53565",
        "user18176",
        "user4255",
        "user82671",
        "user86234",
        "user63815",
        "user51547",
        "user5801",
        "user47053",
        "user12218",
        "user22608",
        "user90110",
        "user35177",
        "user57079",
        "user75505",
        "user89927",
        "user31150",
        "user60772",
        "user59155",
        "user18713",
        "user91562",
        "user66821",
        "user12624",
        "user15800",
        "user7534",
        "user50962",
        "user59937",
        "user86705",
        "user38103",
        "user52015",
        "user86567",
        "user6914",
        "user2486",
        "user65728",
        "user79369",
        "user19517",
        "user27635",
        "user32908",
        "user8467",
        "user87090",
        "user26460",
        "user22266",
        "user84994",
        "user97898",
        "user98387",
        "user4266",
        "user69738",
        "user24611",
        "user43259",
        "user60806",
        "user20764",
        "user73901",
        "user48874",
        "user89643",
        "user79276",
        "user2107",
        "user57994",
        "user48689",
        "user12033",
        "user98337",
        "user55007",
        "user95477",
        "user30099",
        "user78689",
        "user11086",
        "user46162",
        "user11589",
        "user17959",
        "user2713",
        "user61309",
        "user19300",
        "user11173",
        "user81191",
        "user48554",
        "user40775",
        "user45875",
        "user33471",
        "user26115",
        "user40003",
        "user26568",
        "user19732",
        "user8582",
        "user99995",
        "user92902",
        "user15599",
        "user82183",
        "user87137",
        "user39139",
        "user67324",
        "user23096",
        "user41476",
        "user77838",
        "user40992",
        "user85281",
        "user99898",
        "user71151",
        "user9153",
        "user45089",
        "user3388",
        "user83017",
        "user47239",
        "user27420"
    ]
}