{
    "user_id": "user77123",
    "average_retweet_count": "91",
    "average_favorite_count": "433",
    "followers_count": "996",
    "verified": "True",
    "influence_score": "1520",
    "follower_list": [
        "user94213",
        "user6174",
        "user93168",
        "user44741",
        "user28011",
        "user32933",
        "user99591",
        "user18103",
        "user34897",
        "user4488",
        "user21493",
        "user9763",
        "user75235",
        "user64370",
        "user57581",
        "user36172",
        "user72703",
        "user3448",
        "user93992",
        "user47176",
        "user89872",
        "user87809",
        "user49379",
        "user95292",
        "user2574",
        "user74318",
        "user64231",
        "user32214",
        "user60716",
        "user53182",
        "user83316",
        "user44275",
        "user31698",
        "user26366",
        "user40749",
        "user81538",
        "user44921",
        "user10127",
        "user57840",
        "user23880",
        "user59067",
        "user50994",
        "user79913",
        "user16076",
        "user99690",
        "user79813",
        "user37229",
        "user92044",
        "user67364",
        "user51018",
        "user33918",
        "user82793",
        "user6170",
        "user51653",
        "user67479",
        "user50018",
        "user8023",
        "user92599",
        "user86217",
        "user35462",
        "user65082",
        "user98456",
        "user22512",
        "user84594",
        "user65293",
        "user37301",
        "user96289",
        "user33683",
        "user69742",
        "user82795",
        "user72704",
        "user51106",
        "user13612",
        "user51450",
        "user16077",
        "user84146",
        "user3697",
        "user48765",
        "user3338",
        "user22431",
        "user26304",
        "user1013",
        "user97940",
        "user52487",
        "user20634",
        "user19557",
        "user61930",
        "user27930",
        "user77996",
        "user96602",
        "user72313",
        "user8878",
        "user53050",
        "user71460",
        "user95314",
        "user40144",
        "user82852",
        "user4324",
        "user98145",
        "user62704",
        "user27773",
        "user4154",
        "user88097",
        "user73454",
        "user16429",
        "user13120",
        "user6276",
        "user92832",
        "user98198",
        "user10060",
        "user18783",
        "user95875",
        "user9801",
        "user46474",
        "user99811",
        "user17125",
        "user41779",
        "user64840",
        "user60504",
        "user63210",
        "user20114",
        "user60685",
        "user4387",
        "user36335",
        "user77681",
        "user83012",
        "user97274",
        "user92138",
        "user64070",
        "user92023",
        "user8077",
        "user94013",
        "user40957",
        "user61846",
        "user77965",
        "user81",
        "user2526",
        "user67188",
        "user82103",
        "user60464",
        "user29663",
        "user60151",
        "user80103",
        "user1856",
        "user68993",
        "user40480",
        "user12161",
        "user57161",
        "user63375",
        "user71413",
        "user41458",
        "user55103",
        "user26154",
        "user3350",
        "user40248",
        "user81533",
        "user39443",
        "user51130",
        "user5349",
        "user25000",
        "user989",
        "user45175",
        "user9581",
        "user95205",
        "user69908",
        "user48811",
        "user22655",
        "user39116",
        "user52388",
        "user96086",
        "user36005",
        "user84907",
        "user5815",
        "user12027",
        "user37831",
        "user64936",
        "user48047",
        "user76880",
        "user8245",
        "user24644",
        "user93602",
        "user8081",
        "user73354",
        "user87982",
        "user39369",
        "user37314",
        "user43728",
        "user19666",
        "user57224",
        "user81291",
        "user70753",
        "user3574",
        "user35095",
        "user24352",
        "user75160",
        "user76104",
        "user78088",
        "user4839",
        "user10592",
        "user40823",
        "user96131",
        "user43745",
        "user78316",
        "user97229",
        "user79679",
        "user38542",
        "user85114",
        "user54744",
        "user75412",
        "user24672",
        "user64628",
        "user54902",
        "user21502",
        "user58687",
        "user92573",
        "user75701",
        "user79098",
        "user62948",
        "user63487",
        "user17125",
        "user78385",
        "user53710",
        "user57917",
        "user84259",
        "user61356",
        "user85828",
        "user94454",
        "user87131",
        "user23156",
        "user60828",
        "user26947",
        "user38370",
        "user18622",
        "user8106",
        "user61767",
        "user46863",
        "user1413",
        "user73957",
        "user60322",
        "user99965",
        "user58227",
        "user20439",
        "user27591",
        "user11183",
        "user7691",
        "user74904",
        "user62845",
        "user20250",
        "user62984",
        "user2253",
        "user63614",
        "user44760",
        "user83608",
        "user70842",
        "user96109",
        "user53035",
        "user9444",
        "user92261",
        "user17634",
        "user68573",
        "user60584",
        "user3722",
        "user50863",
        "user29410",
        "user17117",
        "user1066",
        "user27394",
        "user49637",
        "user15705",
        "user5256",
        "user34869",
        "user89919",
        "user448",
        "user51095",
        "user42211",
        "user50885",
        "user6291",
        "user89980",
        "user46115",
        "user74189",
        "user36181",
        "user10655",
        "user94894",
        "user14362",
        "user83411",
        "user19527",
        "user47536",
        "user47732",
        "user99855",
        "user84866",
        "user47928",
        "user76187",
        "user31753",
        "user15436",
        "user95940",
        "user79333",
        "user94457",
        "user77113",
        "user72429",
        "user20746",
        "user84764",
        "user24993",
        "user46368",
        "user98518",
        "user94679",
        "user18818",
        "user85281",
        "user99812",
        "user8565",
        "user14317",
        "user26407",
        "user39463",
        "user56322",
        "user83018",
        "user19749",
        "user12462",
        "user19830",
        "user50049",
        "user6119",
        "user97793",
        "user89486",
        "user92670",
        "user63976",
        "user37968",
        "user50789",
        "user77989",
        "user56119",
        "user40724",
        "user35119",
        "user48692",
        "user36574",
        "user27002",
        "user50938",
        "user80044",
        "user3664",
        "user15064",
        "user14712",
        "user81343",
        "user11984",
        "user21965",
        "user14698",
        "user26786",
        "user32449",
        "user3634",
        "user78033",
        "user69516",
        "user98334",
        "user11942",
        "user92119",
        "user42870",
        "user36636",
        "user99650",
        "user16540",
        "user42507",
        "user79877",
        "user10661",
        "user73128",
        "user51311",
        "user16686",
        "user42205",
        "user80394",
        "user90153",
        "user12021",
        "user55985",
        "user92778",
        "user26508",
        "user32661",
        "user46981",
        "user179",
        "user18579",
        "user4975",
        "user56892",
        "user63148",
        "user6664",
        "user50154",
        "user58265",
        "user35305",
        "user16146",
        "user78042",
        "user4753",
        "user17663",
        "user92467",
        "user5040",
        "user39480",
        "user22116",
        "user56115",
        "user94164",
        "user31497",
        "user42396",
        "user32381",
        "user2849",
        "user43776",
        "user6384",
        "user27833",
        "user7002",
        "user47279",
        "user23212",
        "user95731",
        "user55764",
        "user53590",
        "user17473",
        "user39467",
        "user29262",
        "user42364",
        "user99399",
        "user64002",
        "user53646",
        "user78867",
        "user79828",
        "user93931",
        "user65424",
        "user57540",
        "user55822",
        "user33219",
        "user49073",
        "user88003",
        "user78474",
        "user68322",
        "user88227",
        "user35538",
        "user35956",
        "user82870",
        "user55499",
        "user48158",
        "user46412",
        "user67121",
        "user27545",
        "user71187",
        "user98662",
        "user6619",
        "user73823",
        "user88557",
        "user26371",
        "user57164",
        "user86092",
        "user32546",
        "user75218",
        "user76285",
        "user40727",
        "user361",
        "user25836",
        "user15812",
        "user62365",
        "user99079",
        "user27659",
        "user43737",
        "user33146",
        "user50203",
        "user25096",
        "user18067",
        "user30764",
        "user48893",
        "user964",
        "user20826",
        "user33367",
        "user1979",
        "user61699",
        "user81131",
        "user98622",
        "user70513",
        "user80595",
        "user11260",
        "user94787",
        "user59499",
        "user76170",
        "user97670",
        "user4008",
        "user62293",
        "user67865",
        "user18970",
        "user64961",
        "user74166",
        "user72236",
        "user49780",
        "user23261",
        "user19076",
        "user60641",
        "user964",
        "user52669",
        "user84776",
        "user55743",
        "user72314",
        "user95929",
        "user41283",
        "user93642",
        "user78151",
        "user73257",
        "user81698",
        "user16375",
        "user36956",
        "user89674",
        "user99382",
        "user34420",
        "user64400",
        "user8527",
        "user764",
        "user11469",
        "user53330",
        "user55361",
        "user38029",
        "user56327",
        "user91799",
        "user27616",
        "user26899",
        "user29218",
        "user46253",
        "user16758",
        "user50877",
        "user99458",
        "user80885",
        "user30602",
        "user2960",
        "user9655",
        "user18392",
        "user2113",
        "user42892",
        "user8079",
        "user1227",
        "user40922",
        "user82008",
        "user14810",
        "user74608",
        "user21344",
        "user34997",
        "user40829",
        "user5008",
        "user54538",
        "user8099",
        "user26223",
        "user65778",
        "user83805",
        "user80305",
        "user47684",
        "user2976",
        "user13251",
        "user52560",
        "user4702",
        "user25286",
        "user98604",
        "user15412",
        "user43384",
        "user49137",
        "user40686",
        "user16529",
        "user30156",
        "user86440",
        "user88305",
        "user75317",
        "user20980",
        "user7259",
        "user97726",
        "user81039",
        "user45620",
        "user37196",
        "user76204",
        "user18649",
        "user96120",
        "user70244",
        "user96161",
        "user93697",
        "user8655",
        "user36629",
        "user88436",
        "user6067",
        "user95116",
        "user11361",
        "user27607",
        "user18595",
        "user31037",
        "user41659",
        "user6271",
        "user61668",
        "user50508",
        "user90837",
        "user81354",
        "user28283",
        "user85315",
        "user43643",
        "user63293",
        "user18575",
        "user64591",
        "user28979",
        "user94123",
        "user40074",
        "user147",
        "user86711",
        "user58497",
        "user27779",
        "user55678",
        "user75901",
        "user47957",
        "user50737",
        "user69921",
        "user17156",
        "user90352",
        "user7191",
        "user47786",
        "user99451",
        "user46683",
        "user68023",
        "user64151",
        "user67748",
        "user5707",
        "user32391",
        "user79376",
        "user44153",
        "user34639",
        "user25553",
        "user75787",
        "user51385",
        "user86056",
        "user16265",
        "user48665",
        "user43991",
        "user81806",
        "user73803",
        "user94780",
        "user37389",
        "user34734",
        "user61083",
        "user21874",
        "user9261",
        "user96992",
        "user65073",
        "user24975",
        "user26406",
        "user8085",
        "user10453",
        "user97550",
        "user25483",
        "user33073",
        "user46945",
        "user28438",
        "user84906",
        "user95099",
        "user5903",
        "user91979",
        "user1692",
        "user89916",
        "user98033",
        "user62815",
        "user89177",
        "user41843",
        "user42600",
        "user77666",
        "user46450",
        "user41354",
        "user96296",
        "user79899",
        "user32657",
        "user96934",
        "user52979",
        "user91694",
        "user19389",
        "user94227",
        "user32398",
        "user73009",
        "user72326",
        "user24007",
        "user14924",
        "user42493",
        "user61739",
        "user2073",
        "user80180",
        "user68434",
        "user54258",
        "user51753",
        "user97803",
        "user64034",
        "user62001",
        "user91479",
        "user42221",
        "user25863",
        "user78425",
        "user46055",
        "user41574",
        "user82990",
        "user39733",
        "user18172",
        "user29836",
        "user7410",
        "user14457",
        "user7360",
        "user97360",
        "user44046",
        "user12448",
        "user85876",
        "user81915",
        "user74398",
        "user76188",
        "user90696",
        "user19468",
        "user11510",
        "user54298",
        "user62354",
        "user96976",
        "user84362",
        "user20930",
        "user66376",
        "user51928",
        "user76045",
        "user84243",
        "user99484",
        "user70007",
        "user40273",
        "user84991",
        "user43961",
        "user4012",
        "user96833",
        "user79689",
        "user28261",
        "user36824",
        "user19924",
        "user14480",
        "user27519",
        "user41403",
        "user7646",
        "user22349",
        "user46451",
        "user81022",
        "user58982",
        "user52494",
        "user96849",
        "user54954",
        "user76086",
        "user8292",
        "user57924",
        "user58288",
        "user24210",
        "user85149",
        "user65201",
        "user4237",
        "user68028",
        "user68610",
        "user83578",
        "user77645",
        "user70617",
        "user75514",
        "user82333",
        "user11443",
        "user37204",
        "user62430",
        "user95376",
        "user86447",
        "user96028",
        "user10333",
        "user75868",
        "user7231",
        "user80641",
        "user56836",
        "user79155",
        "user70243",
        "user735",
        "user3304",
        "user34799",
        "user33213",
        "user87249",
        "user43800",
        "user62371",
        "user91979",
        "user51088",
        "user31316",
        "user30880",
        "user86419",
        "user99640",
        "user2014",
        "user27451",
        "user65887",
        "user12680",
        "user30969",
        "user18360",
        "user6164",
        "user99281",
        "user47629",
        "user10161",
        "user49433",
        "user55077",
        "user73512",
        "user66674",
        "user18720",
        "user5600",
        "user43328",
        "user2196",
        "user4696",
        "user2460",
        "user85562",
        "user98247",
        "user10859",
        "user52777",
        "user24676",
        "user95924",
        "user6551",
        "user84629",
        "user92110",
        "user11470",
        "user18017",
        "user45871",
        "user99898",
        "user36927",
        "user49299",
        "user17619",
        "user98912",
        "user24019",
        "user73378",
        "user38275",
        "user69750",
        "user80421",
        "user32564",
        "user29308",
        "user78128",
        "user31851",
        "user34527",
        "user54647",
        "user56760",
        "user1671",
        "user44576",
        "user59821",
        "user84036",
        "user26017",
        "user13238",
        "user4668",
        "user16741",
        "user34892",
        "user77019",
        "user5027",
        "user74383",
        "user62107",
        "user82923",
        "user30559",
        "user22028",
        "user98905",
        "user16564",
        "user70195",
        "user29596",
        "user89245",
        "user58518",
        "user56665",
        "user35199",
        "user79431",
        "user98187",
        "user9065",
        "user19779",
        "user61782",
        "user76295",
        "user53415",
        "user52772",
        "user43828",
        "user60067",
        "user46170",
        "user90056",
        "user60554",
        "user55313",
        "user52633",
        "user76438",
        "user86994",
        "user13224",
        "user83300",
        "user65208",
        "user85086",
        "user54265",
        "user7185",
        "user39162",
        "user25395",
        "user84237",
        "user33006",
        "user8614",
        "user69044",
        "user4661",
        "user34395",
        "user3981",
        "user75961",
        "user41572",
        "user94628",
        "user38489",
        "user24644",
        "user22661",
        "user75233",
        "user38778",
        "user25583",
        "user1668",
        "user46677",
        "user50745",
        "user13983",
        "user5217",
        "user73603",
        "user40266",
        "user91582",
        "user99794",
        "user40304",
        "user15696",
        "user99757",
        "user58543",
        "user82161",
        "user87464",
        "user40876",
        "user34063",
        "user64192",
        "user52914",
        "user13215",
        "user56422",
        "user43136",
        "user37590",
        "user74724",
        "user84836",
        "user9084",
        "user94576",
        "user16736",
        "user539",
        "user40804",
        "user62664",
        "user60090",
        "user96495",
        "user78663",
        "user31013",
        "user16616",
        "user759",
        "user97684",
        "user92290",
        "user96850",
        "user16686",
        "user59766",
        "user37050",
        "user84051",
        "user53000",
        "user20143",
        "user29977",
        "user28047",
        "user47650",
        "user43507",
        "user63432",
        "user8544",
        "user45275",
        "user95103",
        "user41185",
        "user68202",
        "user97040",
        "user5969",
        "user52463",
        "user66347",
        "user85239",
        "user34210",
        "user16510",
        "user16780",
        "user26947",
        "user64594",
        "user23379",
        "user75729",
        "user35887",
        "user6202",
        "user32402",
        "user45740",
        "user92563",
        "user5570",
        "user60122",
        "user27481",
        "user68882",
        "user67506",
        "user93851",
        "user25851",
        "user66913",
        "user37541",
        "user76663",
        "user27786",
        "user95775",
        "user12985",
        "user11391",
        "user52425",
        "user2369",
        "user61850",
        "user68300",
        "user38643",
        "user6054",
        "user35143",
        "user69166",
        "user56144",
        "user46331",
        "user82344",
        "user38980",
        "user71812",
        "user1657",
        "user68521",
        "user61330",
        "user15440",
        "user77166",
        "user71631",
        "user92582",
        "user66641",
        "user40049",
        "user10893",
        "user33490",
        "user60488",
        "user67412",
        "user90441",
        "user20068",
        "user52795",
        "user99015"
    ]
}