{
    "screen_name": "user25963",
    "average_retweet_count": "770",
    "average_favorite_count": "2843",
    "followers_count": "1215",
    "verified": "True",
    "influence_score": "1351.91",
    "follower_list": [
        "user55606",
        "user99093",
        "user79863",
        "user77461",
        "user67405",
        "user94328",
        "user85228",
        "user60176",
        "user81427",
        "user87596",
        "user79011",
        "user77720",
        "user80255",
        "user68783",
        "user95810",
        "user98910",
        "user60493",
        "user80566",
        "user70754",
        "user90338",
        "user97846",
        "user58254",
        "user69225",
        "user66803",
        "user82573",
        "user66262",
        "user96616",
        "user57448",
        "user65599",
        "user60396",
        "user88393",
        "user51349",
        "user68103",
        "user87346",
        "user85687",
        "user52402",
        "user56991",
        "user69860",
        "user75310",
        "user54054",
        "user98922",
        "user52163",
        "user56029",
        "user86712",
        "user68666",
        "user94086",
        "user55361",
        "user89959",
        "user82167",
        "user51450",
        "user81004",
        "user59780",
        "user95621",
        "user77632",
        "user81052",
        "user77972",
        "user72193",
        "user81828",
        "user74268",
        "user84244",
        "user58819",
        "user88372",
        "user73777",
        "user84475",
        "user77987",
        "user81956",
        "user87521",
        "user99223",
        "user65274",
        "user77213",
        "user84208",
        "user89715",
        "user83484",
        "user50686",
        "user56498",
        "user51478",
        "user62790",
        "user65347",
        "user57988",
        "user93404",
        "user62276",
        "user66552",
        "user50852",
        "user69349",
        "user89956",
        "user87109",
        "user58587",
        "user86654",
        "user73321",
        "user92819",
        "user61288",
        "user77832",
        "user97876",
        "user58349",
        "user53682",
        "user93242",
        "user76381",
        "user89958",
        "user56184",
        "user98850",
        "user54429",
        "user62233",
        "user56356",
        "user66636",
        "user65161",
        "user66802",
        "user77920",
        "user63669",
        "user59782",
        "user79286",
        "user88457",
        "user92608",
        "user56665",
        "user56491",
        "user72371",
        "user79525",
        "user81714",
        "user99890",
        "user81692",
        "user94675",
        "user99956",
        "user91256",
        "user64698",
        "user55829",
        "user89665",
        "user75940",
        "user52095",
        "user91949",
        "user99729",
        "user96822",
        "user97643",
        "user66431",
        "user82600",
        "user56627",
        "user75648",
        "user66477",
        "user76232",
        "user98107",
        "user65531",
        "user58155",
        "user54326",
        "user71002",
        "user89191",
        "user99173",
        "user66396",
        "user86286",
        "user73945",
        "user59304",
        "user51254",
        "user57573",
        "user70365",
        "user74309",
        "user81601",
        "user85073",
        "user82019",
        "user98615",
        "user73713",
        "user63437",
        "user50190",
        "user82378",
        "user70122",
        "user79639",
        "user56173",
        "user70502",
        "user83443",
        "user94651",
        "user58252",
        "user86974",
        "user87739",
        "user98301",
        "user96921",
        "user81535",
        "user63465",
        "user64188",
        "user50275",
        "user79759",
        "user74564",
        "user98640",
        "user93564",
        "user97711",
        "user96340",
        "user97798",
        "user95447",
        "user50643",
        "user52093",
        "user61097",
        "user73127",
        "user88799",
        "user84264",
        "user75080",
        "user64798",
        "user94299",
        "user58125",
        "user57564",
        "user68892",
        "user82905",
        "user83024",
        "user96235",
        "user85066",
        "user63243",
        "user72313",
        "user54763",
        "user82747",
        "user82651",
        "user79066",
        "user53385",
        "user57840",
        "user58899",
        "user66223",
        "user54437",
        "user56962",
        "user62915",
        "user70928",
        "user56758",
        "user99786",
        "user61231",
        "user97037",
        "user77460",
        "user87685",
        "user75437",
        "user96968",
        "user67289",
        "user82742",
        "user97509",
        "user52915",
        "user80082",
        "user66186",
        "user93728",
        "user81974",
        "user89525",
        "user84443",
        "user58347",
        "user71651",
        "user98419",
        "user57552",
        "user65484",
        "user67290",
        "user73466",
        "user86463",
        "user80427",
        "user94573",
        "user57219",
        "user54767",
        "user50273",
        "user95940",
        "user67732",
        "user83183",
        "user91498",
        "user90988",
        "user90407",
        "user72263",
        "user87376",
        "user56868",
        "user79918",
        "user92023",
        "user60352",
        "user70729",
        "user58870",
        "user99646",
        "user99045",
        "user53477",
        "user94287",
        "user83793",
        "user52063",
        "user55446",
        "user52331",
        "user79747",
        "user71530",
        "user96252",
        "user50369",
        "user64146",
        "user85530",
        "user94329",
        "user52200",
        "user62232",
        "user83232",
        "user92575",
        "user81041",
        "user78046",
        "user61564",
        "user73550",
        "user63694",
        "user66973",
        "user75485",
        "user61949",
        "user86989",
        "user79164",
        "user59702",
        "user83997",
        "user75464",
        "user87394",
        "user92068",
        "user97978",
        "user95807",
        "user58794",
        "user89910",
        "user94811",
        "user85521",
        "user67038",
        "user87159",
        "user95821",
        "user90632",
        "user62242",
        "user88415",
        "user64079",
        "user86885",
        "user60971",
        "user88188",
        "user75685",
        "user98373",
        "user54469",
        "user94619",
        "user97966",
        "user74654",
        "user93172",
        "user73924",
        "user94224",
        "user67866",
        "user99158",
        "user50618",
        "user50105",
        "user86926",
        "user75245",
        "user79646",
        "user73875",
        "user52188",
        "user65077",
        "user74557",
        "user76257",
        "user75808",
        "user95589",
        "user61866",
        "user73516",
        "user83061",
        "user86691",
        "user95757",
        "user70408",
        "user67660",
        "user83713",
        "user57514",
        "user64179",
        "user68301",
        "user72958",
        "user60881",
        "user75529",
        "user79682",
        "user80371",
        "user82039",
        "user70120",
        "user72461",
        "user78666",
        "user88860",
        "user89985",
        "user54755",
        "user91249",
        "user55198",
        "user90006",
        "user66072",
        "user75412",
        "user99454",
        "user77280",
        "user98985",
        "user63285",
        "user91948",
        "user74983",
        "user95233",
        "user58303",
        "user51944",
        "user91925",
        "user87484",
        "user85587",
        "user58763",
        "user96014",
        "user66401",
        "user55028",
        "user93489",
        "user52994",
        "user88058",
        "user80331",
        "user94271",
        "user51091",
        "user78718",
        "user67734",
        "user56342",
        "user70040",
        "user52628",
        "user52778",
        "user99115",
        "user72515",
        "user76983",
        "user85930",
        "user67014",
        "user60836",
        "user97113",
        "user64733",
        "user83148",
        "user91645",
        "user94482",
        "user60691",
        "user70104",
        "user60204",
        "user58093",
        "user73025",
        "user93792",
        "user97216",
        "user62829",
        "user59374",
        "user90270",
        "user66641",
        "user71798",
        "user65254",
        "user63655",
        "user51631",
        "user87208",
        "user51678",
        "user95864",
        "user87668",
        "user97808",
        "user88309",
        "user53129",
        "user86429",
        "user89974",
        "user72017",
        "user60249",
        "user84974",
        "user69461",
        "user53396",
        "user85353",
        "user64005",
        "user61032",
        "user70819",
        "user98657",
        "user79317",
        "user72614",
        "user88185",
        "user76731",
        "user88821",
        "user73433",
        "user80102",
        "user63483",
        "user66778",
        "user70737",
        "user65301",
        "user70324",
        "user73702",
        "user79551",
        "user62767",
        "user73847",
        "user73555",
        "user74210",
        "user80596",
        "user58785",
        "user82184",
        "user83512",
        "user99578",
        "user68440",
        "user79256",
        "user97040",
        "user99365",
        "user92445",
        "user94439",
        "user85719",
        "user89168",
        "user94138",
        "user51105",
        "user89892",
        "user92742",
        "user90285",
        "user50393",
        "user87173",
        "user66090",
        "user57135",
        "user62512",
        "user65055",
        "user58459",
        "user54273",
        "user79428",
        "user80433",
        "user99204",
        "user81748",
        "user93142",
        "user71337",
        "user79579",
        "user97908",
        "user81734",
        "user68459",
        "user87594",
        "user87831",
        "user71165",
        "user62464",
        "user89111",
        "user92497",
        "user79223",
        "user77072",
        "user87945",
        "user69038",
        "user89949",
        "user58900",
        "user61923",
        "user64226",
        "user96316",
        "user96304",
        "user76331",
        "user73284",
        "user67705",
        "user57888",
        "user84583",
        "user88422",
        "user85236",
        "user75544",
        "user81857",
        "user50375",
        "user87785",
        "user76833",
        "user87100",
        "user94746",
        "user80763",
        "user50112",
        "user92591",
        "user72534",
        "user55101",
        "user71279",
        "user99156",
        "user85813",
        "user70358",
        "user71385",
        "user83621",
        "user94309",
        "user61662",
        "user87642",
        "user93088",
        "user62642",
        "user81230",
        "user60664",
        "user58570",
        "user76338",
        "user98122",
        "user66601",
        "user90299",
        "user89879",
        "user70642",
        "user56245",
        "user66683",
        "user81912",
        "user50386",
        "user71986",
        "user70098",
        "user98717",
        "user55161",
        "user69433",
        "user74477",
        "user83375",
        "user91571",
        "user59299",
        "user64997",
        "user86911",
        "user87448",
        "user82442",
        "user95942",
        "user58094",
        "user70046",
        "user56345",
        "user62839",
        "user69766",
        "user88581",
        "user95592",
        "user92912",
        "user72701",
        "user97626",
        "user78972",
        "user51464",
        "user95974",
        "user87428",
        "user79940",
        "user75711",
        "user55316",
        "user67322",
        "user73382",
        "user79107",
        "user96170",
        "user76064",
        "user68687",
        "user60573",
        "user61341",
        "user75742",
        "user76636",
        "user77188",
        "user58210",
        "user74266",
        "user77133",
        "user70371",
        "user54879",
        "user84068",
        "user82634",
        "user88140",
        "user53449",
        "user68083",
        "user84066",
        "user63421",
        "user72834",
        "user82775",
        "user89333",
        "user86695",
        "user81964",
        "user70886",
        "user91790",
        "user67873",
        "user66469",
        "user90605",
        "user81056",
        "user81776",
        "user80653",
        "user72530",
        "user56948",
        "user98819",
        "user93141",
        "user91849",
        "user79058",
        "user76238",
        "user91962",
        "user52259",
        "user78790",
        "user54192",
        "user73980",
        "user55950",
        "user83748",
        "user55034",
        "user83251",
        "user56266",
        "user91324",
        "user57654",
        "user52055",
        "user67618",
        "user66817",
        "user76873",
        "user56803",
        "user59330",
        "user84734",
        "user70458",
        "user53416",
        "user90636",
        "user59086",
        "user77755",
        "user62805",
        "user61218",
        "user85169",
        "user62166",
        "user97741",
        "user98932",
        "user74396",
        "user82825",
        "user76068",
        "user79132",
        "user92138",
        "user67736",
        "user61046",
        "user88728",
        "user63157",
        "user50488",
        "user62762",
        "user82771",
        "user67383",
        "user61229",
        "user72290",
        "user64989",
        "user81590",
        "user98704",
        "user61598",
        "user74443",
        "user77264",
        "user75139",
        "user50747",
        "user53574",
        "user63854",
        "user82489",
        "user86954",
        "user76917",
        "user53883",
        "user65512",
        "user50506",
        "user82818",
        "user64415",
        "user86870",
        "user93466",
        "user56874",
        "user59539",
        "user66134",
        "user94019",
        "user55261",
        "user81393",
        "user99787",
        "user65342",
        "user74011",
        "user93111",
        "user73706",
        "user93723",
        "user52813",
        "user75434",
        "user86898",
        "user51398",
        "user60331",
        "user76551",
        "user51629",
        "user86374",
        "user82314",
        "user84496",
        "user66185",
        "user54531",
        "user60921",
        "user75175",
        "user67725",
        "user80845",
        "user89430",
        "user51024",
        "user97434",
        "user81652",
        "user90138",
        "user72995",
        "user79109",
        "user61187",
        "user66440",
        "user55387",
        "user99557",
        "user71561",
        "user80158",
        "user67648",
        "user88528",
        "user84189",
        "user83331",
        "user69376",
        "user92833",
        "user62239",
        "user71342",
        "user73260",
        "user85049",
        "user70627",
        "user77929",
        "user97624",
        "user85046",
        "user91397",
        "user60601",
        "user65267",
        "user67543",
        "user92241",
        "user98736",
        "user98299",
        "user64342",
        "user94072",
        "user52226",
        "user83335",
        "user80504",
        "user72435",
        "user77230",
        "user62159",
        "user57979",
        "user50327",
        "user94894",
        "user52396",
        "user69402",
        "user50512",
        "user59997",
        "user98639",
        "user89221",
        "user96789",
        "user58024",
        "user61418",
        "user67830",
        "user77799",
        "user55409",
        "user90725",
        "user96811",
        "user94889",
        "user55227",
        "user84297",
        "user76477",
        "user54967",
        "user63152",
        "user73776",
        "user70177",
        "user67742",
        "user69460",
        "user53871",
        "user81976",
        "user67204",
        "user92392",
        "user69751",
        "user62931",
        "user62170",
        "user50183",
        "user55983",
        "user53100",
        "user97101",
        "user96375",
        "user99490",
        "user84693",
        "user67998",
        "user91697",
        "user70765",
        "user93918",
        "user67416",
        "user74476",
        "user52264",
        "user85569",
        "user63440",
        "user65925",
        "user51009",
        "user52746",
        "user60293",
        "user87856",
        "user88105",
        "user78575",
        "user89914",
        "user82548",
        "user98237",
        "user71721",
        "user52416",
        "user93842",
        "user59972",
        "user50291",
        "user67888",
        "user56380",
        "user98493",
        "user69378",
        "user91611",
        "user90456",
        "user80899",
        "user72561",
        "user96880",
        "user99904",
        "user65035",
        "user63331",
        "user82560",
        "user87956",
        "user93255",
        "user58015",
        "user92390",
        "user70907",
        "user82203",
        "user67573",
        "user53579",
        "user73349",
        "user76618",
        "user91724",
        "user69645",
        "user90698",
        "user94899",
        "user63519",
        "user57256",
        "user57729",
        "user92545",
        "user53518",
        "user57749",
        "user72155",
        "user56760",
        "user64010",
        "user67988",
        "user67692",
        "user92178",
        "user80573",
        "user79431",
        "user74917",
        "user91330",
        "user72424",
        "user60495",
        "user95388",
        "user50321",
        "user62551",
        "user67008",
        "user51381",
        "user90642",
        "user79209",
        "user97232",
        "user83244",
        "user92999",
        "user94891",
        "user64484",
        "user65091",
        "user83933",
        "user65995",
        "user60418",
        "user71387",
        "user58485",
        "user79678",
        "user63486",
        "user85027",
        "user74083",
        "user85356",
        "user52665",
        "user84779",
        "user87784",
        "user84578",
        "user50864",
        "user64503",
        "user59857",
        "user87690",
        "user72387",
        "user80378",
        "user56754",
        "user65790",
        "user90459",
        "user72594",
        "user56411",
        "user74184",
        "user68314",
        "user55197",
        "user78518",
        "user52418",
        "user50345",
        "user81440",
        "user68253",
        "user77554",
        "user87528",
        "user83716",
        "user90327",
        "user85214",
        "user73676",
        "user79552",
        "user54571",
        "user69449",
        "user56614",
        "user81173",
        "user75709",
        "user79077",
        "user84140",
        "user84946",
        "user68087",
        "user50996",
        "user66547",
        "user77550",
        "user52411",
        "user63417",
        "user61255",
        "user58047",
        "user92688",
        "user52349",
        "user94332",
        "user65655",
        "user95331",
        "user88307",
        "user59268",
        "user77217",
        "user72198",
        "user66205",
        "user87567",
        "user90745",
        "user99107",
        "user81765",
        "user69613",
        "user74419",
        "user87459",
        "user91190",
        "user64459",
        "user61919",
        "user65360",
        "user71425",
        "user72975",
        "user61112",
        "user50489",
        "user54744",
        "user83511",
        "user62365",
        "user77010",
        "user52086",
        "user94587",
        "user72209",
        "user58200",
        "user97858",
        "user57953",
        "user87828",
        "user84296",
        "user61221",
        "user98017",
        "user93717",
        "user85226",
        "user54329",
        "user56433",
        "user50334",
        "user78810",
        "user57212",
        "user95792",
        "user92587",
        "user54594",
        "user64801",
        "user76673",
        "user73675",
        "user50195",
        "user74523",
        "user84438",
        "user66162",
        "user79633",
        "user52230",
        "user81789",
        "user86673",
        "user73114",
        "user62051",
        "user62712",
        "user91845",
        "user58990",
        "user71467",
        "user75939",
        "user88351",
        "user54367",
        "user50740",
        "user72688",
        "user93354",
        "user66438",
        "user62259",
        "user84186",
        "user86457",
        "user79179",
        "user87821",
        "user99330",
        "user89197",
        "user81836",
        "user78205",
        "user62740",
        "user74558",
        "user58956",
        "user72814",
        "user86523",
        "user87228",
        "user58708",
        "user94463",
        "user68482",
        "user53480",
        "user83458",
        "user52149",
        "user59279",
        "user62227",
        "user62098",
        "user97975",
        "user66422",
        "user81035",
        "user51065",
        "user92687",
        "user56823",
        "user68722",
        "user69274",
        "user52975",
        "user89983",
        "user53168",
        "user53427",
        "user98104",
        "user61171",
        "user60434",
        "user93536",
        "user64203",
        "user75615",
        "user96080",
        "user56839",
        "user93514",
        "user89766",
        "user65656",
        "user97390",
        "user54056",
        "user74035",
        "user66371",
        "user93942",
        "user88107",
        "user71815",
        "user58633",
        "user83622",
        "user51867",
        "user65793",
        "user51987",
        "user73545",
        "user93386",
        "user74016",
        "user69407",
        "user77946",
        "user51070",
        "user82435",
        "user51025",
        "user68671",
        "user92123",
        "user94806",
        "user67602",
        "user90086",
        "user53896",
        "user66727",
        "user62558",
        "user95231",
        "user97788",
        "user57556",
        "user86943",
        "user57859",
        "user52893",
        "user67068",
        "user96360",
        "user92862",
        "user79009",
        "user79014",
        "user88480",
        "user59946",
        "user88631",
        "user57515",
        "user52849",
        "user79601",
        "user98106",
        "user95888",
        "user99735",
        "user57732",
        "user83895",
        "user91597",
        "user64315",
        "user75328",
        "user69278",
        "user89702",
        "user63265",
        "user51707",
        "user86073",
        "user97574",
        "user69993",
        "user86020",
        "user64130",
        "user87232",
        "user76485",
        "user84336",
        "user52080",
        "user97298",
        "user55655",
        "user55009",
        "user60160",
        "user70410",
        "user81142",
        "user93566",
        "user94039",
        "user52632",
        "user82865",
        "user93289",
        "user72802",
        "user54870",
        "user56467",
        "user84802",
        "user63238",
        "user73305",
        "user94807",
        "user51781",
        "user76062",
        "user91993",
        "user74424",
        "user95224",
        "user65486",
        "user75733",
        "user96164",
        "user80683",
        "user96514",
        "user57976",
        "user60587",
        "user69415",
        "user92612",
        "user52263",
        "user61563",
        "user96009",
        "user97467",
        "user60400",
        "user52933",
        "user77677",
        "user64054",
        "user99980",
        "user96828",
        "user61487",
        "user85459",
        "user89516",
        "user68806",
        "user78254",
        "user71104",
        "user55694",
        "user79246",
        "user68334",
        "user76185",
        "user71844",
        "user68307",
        "user69995",
        "user61208",
        "user68909",
        "user93326",
        "user93410",
        "user80403",
        "user50198",
        "user83355",
        "user85493",
        "user87050",
        "user66198",
        "user89387",
        "user97086",
        "user61900",
        "user74449",
        "user61533",
        "user59013",
        "user72282",
        "user88710",
        "user71849",
        "user55203",
        "user81806",
        "user60244",
        "user83744",
        "user77370",
        "user73132",
        "user98498",
        "user82279",
        "user75542",
        "user50121",
        "user64487",
        "user84317",
        "user77472",
        "user84603",
        "user69778",
        "user51161",
        "user53340",
        "user84348",
        "user82366",
        "user92089",
        "user73082",
        "user67006"
    ]
}