{
    "screen_name": "user27688",
    "average_retweet_count": "693",
    "average_favorite_count": "307",
    "followers_count": "36",
    "verified": "False",
    "influence_score": "299.38",
    "follower_list": [
        "user57000",
        "user93865",
        "user68449",
        "user90012",
        "user63028",
        "user76501",
        "user61504",
        "user67286",
        "user51286",
        "user60581",
        "user85603",
        "user98108",
        "user63323",
        "user54811",
        "user66767",
        "user84896",
        "user68544",
        "user51337",
        "user57003",
        "user67660",
        "user90134",
        "user70574",
        "user50660",
        "user76738",
        "user75239",
        "user80138",
        "user62957",
        "user71416",
        "user56064",
        "user70867",
        "user93395",
        "user53009",
        "user86001",
        "user94807",
        "user62697",
        "user52741"
    ]
}