{
    "screen_name": "user3105",
    "average_retweet_count": "290",
    "average_favorite_count": "2942",
    "followers_count": "40",
    "verified": "True",
    "influence_score": "615.84",
    "follower_list": [
        "user79944",
        "user91788",
        "user91251",
        "user95360",
        "user93887",
        "user70216",
        "user71279",
        "user88456",
        "user86939",
        "user74754",
        "user91987",
        "user66092",
        "user88533",
        "user64273",
        "user55076",
        "user73016",
        "user53844",
        "user73132",
        "user64096",
        "user78949",
        "user84472",
        "user73531",
        "user69212",
        "user64615",
        "user67456",
        "user96243",
        "user74482",
        "user99616",
        "user99980",
        "user92154",
        "user94289",
        "user70034",
        "user86084",
        "user52858",
        "user96527",
        "user86456",
        "user79087",
        "user80420",
        "user85942",
        "user93161"
    ]
}