{
    "screen_name": "user16545",
    "average_retweet_count": "259",
    "average_favorite_count": "2258",
    "followers_count": "21",
    "verified": "False",
    "influence_score": "479.83",
    "follower_list": [
        "user83289",
        "user63588",
        "user67802",
        "user80573",
        "user93608",
        "user70185",
        "user57254",
        "user50508",
        "user98031",
        "user59092",
        "user69316",
        "user72358",
        "user77203",
        "user90332",
        "user76620",
        "user62243",
        "user74217",
        "user92576",
        "user63426",
        "user69663",
        "user72120"
    ]
}