{
    "screen_name": "user18914",
    "average_retweet_count": "312",
    "average_favorite_count": "2661",
    "followers_count": "19",
    "verified": "False",
    "influence_score": "564.83",
    "follower_list": [
        "user84297",
        "user74849",
        "user85529",
        "user86868",
        "user52424",
        "user85082",
        "user76319",
        "user53533",
        "user93016",
        "user53300",
        "user50724",
        "user58389",
        "user54152",
        "user87230",
        "user71605",
        "user54222",
        "user62604",
        "user61183",
        "user82655"
    ]
}