{
    "screen_name": "user33343",
    "average_retweet_count": "339",
    "average_favorite_count": "2233",
    "followers_count": "31",
    "verified": "False",
    "influence_score": "506.98",
    "follower_list": [
        "user72901",
        "user50017",
        "user63562",
        "user54734",
        "user92058",
        "user89464",
        "user81046",
        "user64563",
        "user58209",
        "user82824",
        "user77350",
        "user94050",
        "user70764",
        "user65793",
        "user63327",
        "user58058",
        "user78892",
        "user93815",
        "user72928",
        "user85826",
        "user88415",
        "user64094",
        "user65496",
        "user77420",
        "user82642",
        "user72671",
        "user80978",
        "user52552",
        "user94468",
        "user50630",
        "user72839"
    ]
}