{
    "screen_name": "user742",
    "average_retweet_count": "738",
    "average_favorite_count": "2278",
    "followers_count": "28",
    "verified": "False",
    "influence_score": "644.8",
    "follower_list": [
        "user1293",
        "user19808",
        "user49633",
        "user12277",
        "user14164",
        "user12472",
        "user15663",
        "user43624",
        "user13292",
        "user9374",
        "user47649",
        "user29255",
        "user20702",
        "user8025",
        "user10819",
        "user13460",
        "user23470",
        "user45035",
        "user15285",
        "user26397",
        "user8760",
        "user17077",
        "user21995",
        "user34026",
        "user5923",
        "user47866",
        "user37474",
        "user21366"
    ]
}